{"assets":{"DC042435D5E7A65B7B170ABBBF68248F":{"type":"texture","index":4,"assetRequest":{"type":"slide","state":"outgoing","slide":"C56D3327-A5BC-4415-8117-EA1CC57C360C"},"url":"assets/DC042435D5E7A65B7B170ABBBF68248F.svg","width":1024,"height":768},"CA24D257A3F0C5CF4C7916D20EA1AB31":{"type":"texture","index":5,"assetRequest":{"type":"slide","state":"incoming","slide":"4C498532-31A4-4238-8A2C-AC03D702106E"},"url":"assets/CA24D257A3F0C5CF4C7916D20EA1AB31.svg","width":1024,"height":768}},"events":[{"effects":[{"beginTime":0,"baseLayer":{"animations":[],"initialState":{"affineTransform":[1,0,0,1,0,0],"masksToBounds":true,"rotation":0,"scale":1,"position":{"pointX":512,"pointY":384},"width":1024,"sublayerTransform":[1,0,0,0,0,1,0,0,0,0,1,0,0,0,0,1],"contentsRect":{"y":0,"x":0,"width":1,"height":1},"opacity":1,"edgeAntialiasingMask":0,"height":768,"hidden":false,"anchorPoint":{"pointX":0.5,"pointY":0.5}},"objectID":"0","layers":[{"animations":[],"initialState":{"affineTransform":[1,0,0,1,0,0],"masksToBounds":false,"rotation":0,"scale":1,"position":{"pointX":512,"pointY":384},"width":1024,"sublayerTransform":[1,0,0,0,0,1,0,0,0,0,1,-0.0004922987690640373,0,0,0,1],"contentsRect":{"y":0,"x":0,"width":1,"height":1},"opacity":1,"edgeAntialiasingMask":15,"height":768,"hidden":false,"anchorPoint":{"pointX":0.5,"pointY":0.5}},"layers":[{"animations":[],"layers":[],"initialState":{"affineTransform":[1,0,0,1,0,0],"masksToBounds":false,"rotation":0,"scale":1,"position":{"pointX":512,"pointY":384},"width":1024,"sublayerTransform":[1,0,0,0,0,1,0,0,0,0,1,0,0,0,0,1],"contentsRect":{"y":0,"x":0,"width":1,"height":1},"opacity":1,"edgeAntialiasingMask":0,"height":768,"hidden":false,"anchorPoint":{"pointX":0.5,"pointY":0.5}},"texture":"CA24D257A3F0C5CF4C7916D20EA1AB31"},{"animations":[{"from":{"scalar":false},"beginTime":0,"repeatCount":0,"fillMode":"both","property":"hidden","duration":0.01,"to":{"scalar":true}}],"layers":[],"initialState":{"affineTransform":[1,0,0,1,0,0],"masksToBounds":false,"rotation":0,"scale":1,"position":{"pointX":512,"pointY":384},"width":1024,"sublayerTransform":[1,0,0,0,0,1,0,0,0,0,1,0,0,0,0,1],"contentsRect":{"y":0,"x":0,"width":1,"height":1},"opacity":1,"edgeAntialiasingMask":0,"height":768,"hidden":false,"anchorPoint":{"pointX":0.5,"pointY":0.5}},"texture":"DC042435D5E7A65B7B170ABBBF68248F"}]}]},"effects":[],"duration":0.01,"type":"transition","name":"none","objectID":"0"}],"automaticPlay":false,"hyperlinks":[],"accessibility":[{"text":"100 oC","targetRectangle":{"y":322.0506893992424,"x":660.047607421875,"width":81.19726592488587,"height":32.00000018294668}},{"text":"100 oC","targetRectangle":{"y":322.0506893992424,"x":828.4088134765625,"width":81.19726592488587,"height":32.00000018294668}},{"text":"Veden lämmittämiseen","targetRectangle":{"y":269.9640499949455,"x":168.8534088134766,"width":286.78125,"height":32}},{"text":"Mutta kuinka paljon!?!","targetRectangle":{"y":635.6350703239441,"x":346.7424011230469,"width":364.939453125,"height":41}},{"text":"Mihin kiukaan lämpöenergia kului?","targetRectangle":{"y":170,"x":113.9999995231628,"width":566.859375,"height":41}},{"text":"pasted-image.jpg","targetRectangle":{"y":540.6009521484375,"x":688.9612426757812,"width":166.6235198974609,"height":173.1059875488281}},{"text":"100 oC","targetRectangle":{"y":322.0506893992424,"x":335.3953247070312,"width":81.19726592488587,"height":32.00000018294668}},{"text":"Fysiikkaa saunassa","targetRectangle":{"y":60,"x":238.876220703125,"width":546.24755859375,"height":74}},{"text":"pasted-image.jpg","targetRectangle":{"y":540.6009521484375,"x":195.5973510742188,"width":166.6235198974609,"height":173.1059875488281}},{"text":"10 oC","targetRectangle":{"y":322.0506893992424,"x":176.3495025634766,"width":64.01171904988587,"height":32.00000018294668}},{"text":"Veden höyrystämiseen","targetRectangle":{"y":269.9640499949455,"x":645.363525390625,"width":279.986328125,"height":32}}],"baseLayer":{"animations":[],"initialState":{"affineTransform":[1,0,0,1,0,0],"masksToBounds":true,"rotation":0,"scale":1,"position":{"pointX":512,"pointY":384},"width":1024,"sublayerTransform":[1,0,0,0,0,1,0,0,0,0,1,0,0,0,0,1],"contentsRect":{"y":0,"x":0,"width":1,"height":1},"opacity":1,"edgeAntialiasingMask":0,"height":768,"hidden":false,"anchorPoint":{"pointX":0.5,"pointY":0.5}},"objectID":"0","layers":[{"animations":[],"initialState":{"affineTransform":[1,0,0,1,0,0],"masksToBounds":false,"rotation":0,"scale":1,"position":{"pointX":512,"pointY":384},"width":1024,"sublayerTransform":[1,0,0,0,0,1,0,0,0,0,1,-0.0004922987690640373,0,0,0,1],"contentsRect":{"y":0,"x":0,"width":1,"height":1},"opacity":1,"edgeAntialiasingMask":15,"height":768,"hidden":false,"anchorPoint":{"pointX":0.5,"pointY":0.5}},"layers":[{"animations":[],"layers":[],"initialState":{"affineTransform":[1,0,0,1,0,0],"masksToBounds":false,"rotation":0,"scale":1,"position":{"pointX":512,"pointY":384},"width":1024,"sublayerTransform":[1,0,0,0,0,1,0,0,0,0,1,0,0,0,0,1],"contentsRect":{"y":0,"x":0,"width":1,"height":1},"opacity":1,"edgeAntialiasingMask":0,"height":768,"hidden":false,"anchorPoint":{"pointX":0.5,"pointY":0.5}},"texture":"DC042435D5E7A65B7B170ABBBF68248F"}]}]}}]}